Workbook

Sheet Sanitized
A1: SaleDateSanitized | B1: PorscheModelSanitized | C1: ModelYearSanitized | D1: SalesPriceSanitized | E1: VehicleMileageSanitized | F1: PayMethodSanitized | G1: CitySanitized | H1: StateSanitized | I1: DeliveryStatusSanitized | J1: PriceBand | K1: DeliveryStatusGrouped
A2: INVALID | B2: 718 Cayman | C2: 2022 | D2: 79500 | E2: 9800 | F2: Credit Card | G2: Boston | H2: MA | I2: Delivered | J2: =IF(D2<=Mapeamento!$E$2,"Até US$ 100 mil",IF(D2<=Mapeamento!$E$3,"US$ 100–200 mil","Acima de US$ 200 mil")) -> Até US$ 100 mil | K2: =IFERROR(INDEX(Mapeamento!$B$3:$B$12,MATCH(I2,Mapeamento!$A$3:$A$12,0)),"NÃO MAPEADO") -> Concluído
A3: 2024-03-14 | B3: 911 Turbo S | C3: 2024 | D3: 235000 | E3: 1200 | F3: Wire Transfer | G3: Seattle | H3: WA | I3: Delivered | J3: =IF(D3<=Mapeamento!$E$2,"Até US$ 100 mil",IF(D3<=Mapeamento!$E$3,"US$ 100–200 mil","Acima de US$ 200 mil")) -> Acima de US$ 200 mil | K3: =IFERROR(INDEX(Mapeamento!$B$3:$B$12,MATCH(I3,Mapeamento!$A$3:$A$12,0)),"NÃO MAPEADO") -> Concluído
A4: 2024-04-18 | B4: Cayenne Coupe | C4: 2023 | D4: 112750 | E4: 6400 | F4: Financing | G4: Austin | H4: TX | I4: In Transit | J4: =IF(D4<=Mapeamento!$E$2,"Até US$ 100 mil",IF(D4<=Mapeamento!$E$3,"US$ 100–200 mil","Acima de US$ 200 mil")) -> US$ 100–200 mil | K4: =IFERROR(INDEX(Mapeamento!$B$3:$B$12,MATCH(I4,Mapeamento!$A$3:$A$12,0)),"NÃO MAPEADO") -> Em logística
A5: INVALID | B5: Macan S | C5: 2021 | D5: 68900 | E5: 28 | F5: Cash | G5: Denver | H5: CO | I5: Pending | J5: =IF(D5<=Mapeamento!$E$2,"Até US$ 100 mil",IF(D5<=Mapeamento!$E$3,"US$ 100–200 mil","Acima de US$ 200 mil")) -> Até US$ 100 mil | K5: =IFERROR(INDEX(Mapeamento!$B$3:$B$12,MATCH(I5,Mapeamento!$A$3:$A$12,0)),"NÃO MAPEADO") -> Em aprovação
A6: 2024-05-22 | B6: Taycan 4S | C6: 2024 | D6: 121000 | E6: 0 | F6: Bank Transfer | G6: Los Angeles | H6: CA | I6: Delivered | J6: =IF(D6<=Mapeamento!$E$2,"Até US$ 100 mil",IF(D6<=Mapeamento!$E$3,"US$ 100–200 mil","Acima de US$ 200 mil")) -> US$ 100–200 mil | K6: =IFERROR(INDEX(Mapeamento!$B$3:$B$12,MATCH(I6,Mapeamento!$A$3:$A$12,0)),"NÃO MAPEADO") -> Concluído
A7: 2024-08-06 | B7: Panamera 4 | C7: 2023 | D7: 104500 | E7: 14500 | F7: Credit Card | G7: Miami | H7: FL | I7: Cancelled | J7: =IF(D7<=Mapeamento!$E$2,"Até US$ 100 mil",IF(D7<=Mapeamento!$E$3,"US$ 100–200 mil","Acima de US$ 200 mil")) -> US$ 100–200 mil | K7: =IFERROR(INDEX(Mapeamento!$B$3:$B$12,MATCH(I7,Mapeamento!$A$3:$A$12,0)),"NÃO MAPEADO") -> Cancelado
A8: 2024-07-11 | B8: 911 Carrera S | C8: 2020 | D8: 96300 | E8: 41000 | F8: Lease | G8: New York | H8: NY | I8: Delivered | J8: =IF(D8<=Mapeamento!$E$2,"Até US$ 100 mil",IF(D8<=Mapeamento!$E$3,"US$ 100–200 mil","Acima de US$ 200 mil")) -> Até US$ 100 mil | K8: =IFERROR(INDEX(Mapeamento!$B$3:$B$12,MATCH(I8,Mapeamento!$A$3:$A$12,0)),"NÃO MAPEADO") -> Concluído
A9: INVALID | B9: Cayenne E-Hybrid | C9: 2022 | D9: 89750 | E9: 11744 | F9: Wire Transfer | G9: San Diego | H9: CA | I9: Pending Approval | J9: =IF(D9<=Mapeamento!$E$2,"Até US$ 100 mil",IF(D9<=Mapeamento!$E$3,"US$ 100–200 mil","Acima de US$ 200 mil")) -> Até US$ 100 mil | K9: =IFERROR(INDEX(Mapeamento!$B$3:$B$12,MATCH(I9,Mapeamento!$A$3:$A$12,0)),"NÃO MAPEADO") -> Em aprovação
A10: 2024-08-19 | B10: 718 Boxster | C10: 2021 | D10: 73500 | E10: 22300 | F10: Debit Card | G10: Chicago | H10: IL | I10: Shipped | J10: =IF(D10<=Mapeamento!$E$2,"Até US$ 100 mil",IF(D10<=Mapeamento!$E$3,"US$ 100–200 mil","Acima de US$ 200 mil")) -> Até US$ 100 mil | K10: =IFERROR(INDEX(Mapeamento!$B$3:$B$12,MATCH(I10,Mapeamento!$A$3:$A$12,0)),"NÃO MAPEADO") -> Em logística
A11: 2024-09-02 | B11: Macan GTS | C11: 2024 | D11: 95000 | E11: 3500 | F11: Financing | G11: Phoenix | H11: AZ | I11: In Transit | J11: =IF(D11<=Mapeamento!$E$2,"Até US$ 100 mil",IF(D11<=Mapeamento!$E$3,"US$ 100–200 mil","Acima de US$ 200 mil")) -> Até US$ 100 mil | K11: =IFERROR(INDEX(Mapeamento!$B$3:$B$12,MATCH(I11,Mapeamento!$A$3:$A$12,0)),"NÃO MAPEADO") -> Em logística
A12: 2024-09-17 | B12: Taycan Turbo | C12: 2023 | D12: 153200.5 | E12: 11 | F12: ACH Payment | G12: Dallas | H12: TX | I12: Delivered | J12: =IF(D12<=Mapeamento!$E$2,"Até US$ 100 mil",IF(D12<=Mapeamento!$E$3,"US$ 100–200 mil","Acima de US$ 200 mil")) -> US$ 100–200 mil | K12: =IFERROR(INDEX(Mapeamento!$B$3:$B$12,MATCH(I12,Mapeamento!$A$3:$A$12,0)),"NÃO MAPEADO") -> Concluído
A13: INVALID | B13: 911 GT3 | C13: 2024 | D13: 241000 | E13: 750 | F13: Wire Transfer | G13: Las Vegas | H13: NV | I13: Pending | J13: =IF(D13<=Mapeamento!$E$2,"Até US$ 100 mil",IF(D13<=Mapeamento!$E$3,"US$ 100–200 mil","Acima de US$ 200 mil")) -> Acima de US$ 200 mil | K13: =IFERROR(INDEX(Mapeamento!$B$3:$B$12,MATCH(I13,Mapeamento!$A$3:$A$12,0)),"NÃO MAPEADO") -> Em aprovação
... A101: 2027-10-01 | B101: 911 Dakar | C101: 2024 | D101: 271700 | E101: 1050 | F101: Lease | G101: New Orleans | H101: LA | I101: Delivered | J101: =IF(D101<=Mapeamento!$E$2,"Até US$ 100 mil",IF(D101<=Mapeamento!$E$3,"US$ 100–200 mil","Acima de US$ 200 mil")) -> Acima de US$ 200 mil | K101: =IFERROR(INDEX(Mapeamento!$B$3:$B$12,MATCH(I101,Mapeamento!$A$3:$A$12,0)),"NÃO MAPEADO") -> Concluído

Sheet Mapeamento
A1: Mapeamento de status de entrega | D1: Faixas de preço (US$)
A2: Status original | B2: Status agrupado | D2: Limite superior – faixa 1 | E2: 100000
A3: Delivered | B3: Concluído | D3: Limite superior – faixa 2 | E3: 200000
A4: Pending | B4: Em aprovação
A5: Pending Approval | B5: Em aprovação | D5: Premissas (editáveis, em azul):
A6: Pending Review | B6: Em aprovação | D6: Faixas: até E2; acima de E2 até E3; acima de E3. Limites escolhidos por mim, não vêm da base.
A7: Awaiting Review | B7: Em aprovação | D7: "Pending" foi classificado como Em aprovação por suposição; a base não diz se é aprovação ou logística.
A8: In Transit | B8: Em logística | D8: Alterar o grupo na coluna B atualiza a coluna K da aba Sanitized.
A9: Shipped | B9: Em logística
A10: Awaiting Delivery | B10: Em logística
A11: Awaiting Pickup | B11: Em logística
A12: Cancelled | B12: Cancelado
